{
	"pages": [{
			"path": "pages/index/index",
			"style": {
				"navigationBarTitleText": "uni-app"
			}
		},
		{
			"path": "pages/basics/background",
			"style": {}
		},
		{
			"path": "pages/basics/text",
			"style": {}
		},
    {
    	"path": "pages/demo/tabs/tabs",
    	"style": {}
    }
	],
	"easycom": {
		"autoscan": true,
		"custom": {
			"zen-(.*)": "@/components/zen-$1/zen-$1.vue"
		}
	},
	"globalStyle": {
		"navigationBarTextStyle": "black",
		"navigationBarTitleText": "uni-app",
		"navigationBarBackgroundColor": "#F8F8F8",
		"backgroundColor": "#F8F8F8",
		"navigationStyle": "custom"
	}
}